lowrankdensity/__init__.py
lowrankdensity/datasets/__init__.py
lowrankdensity/datasets/generate_samples.py
lowrankdensity/models/__init__.py
lowrankdensity/models/continuous.py
lowrankdensity/models/discrete.py
lowrankdensity_demo_2025-0.0.3.dist-info/METADATA
lowrankdensity_demo_2025-0.0.3.dist-info/WHEEL
lowrankdensity_demo_2025-0.0.3.dist-info/top_level.txt
lowrankdensity_demo_2025-0.0.3.dist-info/RECORD
