Metadata-Version: 2.4
Name: lowrankdensity_demo_2025
Version: 0.0.3
Summary: This package does amazing things.
Home-page: https://github.com/yohila/Summer_School_Package
Author: Hi Paris
Author-email: "Hi! Paris" <contact@hiparis.com>
License: MIT
Classifier: License :: OSI Approved :: MIT License
Requires-Dist: termcolor<2,>=1.1.0
Requires-Dist: numpy
Requires-Dist: scipy
